{
  "id": "瑞士联邦政府_8_1768162656",
  "title": "More about «New process for stable, long-lasting all-solid-state batteries»",
  "titleChinese": "More about «New process for stable, long-lasting all-solid-state batteries»",
  "source": "瑞士联邦政府",
  "url": "https://www.admin.ch/en/newnsb/1YGkS6bug7p4pY_22wHIA",
  "publishTime": "2026-01-11T20:17:36.759023+00:00",
  "category": "government",
  "language": "en",
  "extractedAt": "2026-01-11T20:17:36.759025+00:00",
  "extractedBy": "github-pages-crawler"
}