{
  "id": "瑞士联邦政府_9_1764260319",
  "title": "More about «New recipients of occupational pensions in 2024:  upward trend in lump-sum payments continues»",
  "titleChinese": "More about «New recipients of occupational pensions in 2024:  upward trend in lump-sum payments continues»",
  "source": "瑞士联邦政府",
  "url": "https://www.admin.ch/en/newnsb/1rxs8YVJAO43Fmnyf5mbH",
  "publishTime": "2025-11-27T16:18:39.679775+00:00",
  "category": "government",
  "language": "en",
  "extractedAt": "2025-11-27T16:18:39.679776+00:00",
  "extractedBy": "github-pages-crawler"
}