{
  "id": "瑞士联邦政府_8_1773952248",
  "title": "More about «ESA Council meeting at delegate level takes place in Switzerland»",
  "titleChinese": "More about «ESA Council meeting at delegate level takes place in Switzerland»",
  "source": "瑞士联邦政府",
  "url": "https://www.admin.ch/en/newnsb/sAUFbCDYdpPtgenlSlaCK",
  "publishTime": "2026-03-19T20:30:48.018661+00:00",
  "category": "government",
  "language": "en",
  "extractedAt": "2026-03-19T20:30:48.018663+00:00",
  "extractedBy": "github-pages-crawler"
}