{
  "id": "瑞士联邦政府_12_1770620321",
  "title": "More about «Deputy State Secretary for Security Policy attends Summit on Responsible Use of AI in the Military Domain in Spain»",
  "titleChinese": "More about «Deputy State Secretary for Security Policy attends Summit on Responsible Use of AI in the Military Domain in Spain»",
  "source": "瑞士联邦政府",
  "url": "https://www.admin.ch/en/newnsb/vT-znG-NnS6Z",
  "publishTime": "2026-02-09T06:58:41.781331+00:00",
  "category": "government",
  "language": "en",
  "extractedAt": "2026-02-09T06:58:41.781333+00:00",
  "extractedBy": "github-pages-crawler"
}