{
  "id": "瑞士联邦政府_9_1764843518",
  "title": "More about «Switzerland and the USA launch “A-VIPER” research project focusing on the automated identification of software vulnerabilities»",
  "titleChinese": "More about «Switzerland and the USA launch “A-VIPER” research project focusing on the automated identification of software vulnerabilities»",
  "source": "瑞士联邦政府",
  "url": "https://www.admin.ch/en/newnsb/hhwjvgaubG9O3Y-EfeEkA",
  "publishTime": "2025-12-04T10:18:38.416642+00:00",
  "category": "government",
  "language": "en",
  "extractedAt": "2025-12-04T10:18:38.416643+00:00",
  "extractedBy": "github-pages-crawler"
}