{
  "id": "瑞士联邦政府_12_1762849225",
  "title": "More about «President Keller-Sutter to travel to Poland for talks with President Nawrocki and Prime Minister Tusk»",
  "titleChinese": "More about «President Keller-Sutter to travel to Poland for talks with President Nawrocki and Prime Minister Tusk»",
  "source": "瑞士联邦政府",
  "url": "https://www.admin.ch/en/newnsb/rseaTEyqYYKMq1fBgUOrs",
  "publishTime": "2025-11-11T08:20:25.707275+00:00",
  "category": "government",
  "language": "en",
  "extractedAt": "2025-11-11T08:20:25.707276+00:00",
  "extractedBy": "github-pages-crawler"
}