{
  "id": "瑞士联邦政府_12_1769854748",
  "title": "More about «Six new National Centres of Competence in Research strengthen Swiss cutting-edge research in strategically important areas»",
  "titleChinese": "More about «Six new National Centres of Competence in Research strengthen Swiss cutting-edge research in strategically important areas»",
  "source": "瑞士联邦政府",
  "url": "https://www.admin.ch/en/newnsb/JEYzIEzRw1QFKXIpHWlxC",
  "publishTime": "2026-01-31T10:19:08.312918+00:00",
  "category": "government",
  "language": "en",
  "extractedAt": "2026-01-31T10:19:08.312921+00:00",
  "extractedBy": "github-pages-crawler"
}