{
  "id": "瑞士联邦政府_12_1765923314",
  "title": "More about «Social assistance rate remained below long-term average in 2024 – modernised Social Assistance Statistics for more relevant and timely results»",
  "titleChinese": "More about «Social assistance rate remained below long-term average in 2024 – modernised Social Assistance Statistics for more relevant and timely results»",
  "source": "瑞士联邦政府",
  "url": "https://www.admin.ch/en/newnsb/4j3hfwwf7LC5D13sAwqo5",
  "publishTime": "2025-12-16T22:15:14.527895+00:00",
  "category": "government",
  "language": "en",
  "extractedAt": "2025-12-16T22:15:14.527897+00:00",
  "extractedBy": "github-pages-crawler"
}