{
  "id": "瑞士联邦政府_13_1774239874",
  "title": "More about «ESA Council meeting at delegate level takes place in Switzerland»",
  "titleChinese": "More about «ESA Council meeting at delegate level takes place in Switzerland»",
  "source": "瑞士联邦政府",
  "url": "https://www.admin.ch/en/newnsb/sAUFbCDYdpPtgenlSlaCK",
  "publishTime": "2026-03-23T04:24:34.485038+00:00",
  "category": "government",
  "language": "en",
  "extractedAt": "2026-03-23T04:24:34.485040+00:00",
  "extractedBy": "github-pages-crawler"
}