{
  "id": "瑞士联邦政府_12_1767939980",
  "title": "More about «Federal Council freezes any assets held in Switzerland by Nicolás Maduro»",
  "titleChinese": "More about «Federal Council freezes any assets held in Switzerland by Nicolás Maduro»",
  "source": "瑞士联邦政府",
  "url": "https://www.admin.ch/en/newnsb/4mdMVbqPTwY-5XoVHeNVP",
  "publishTime": "2026-01-09T06:26:20.430587+00:00",
  "category": "government",
  "language": "en",
  "extractedAt": "2026-01-09T06:26:20.430589+00:00",
  "extractedBy": "github-pages-crawler"
}