{
  "id": "瑞士联邦政府_7_1759177860",
  "title": "More about «Restitution of assets to the benefit of the population of Equatorial Guinea»",
  "titleChinese": "More about «Restitution of assets to the benefit of the population of Equatorial Guinea»",
  "source": "瑞士联邦政府",
  "url": "https://www.admin.ch/en/newnsb/OzfIJ6ZKlECvCIN8SLjc8",
  "publishTime": "2025-09-29T20:31:00.524171+00:00",
  "category": "government",
  "language": "en",
  "extractedAt": "2025-09-29T20:31:00.524173+00:00",
  "extractedBy": "github-pages-crawler"
}