{
  "id": "瑞士联邦政府_10_1760646958",
  "title": "More about «Agreement with India on mobility and transport infrastructure»",
  "titleChinese": "More about «Agreement with India on mobility and transport infrastructure»",
  "source": "瑞士联邦政府",
  "url": "https://www.admin.ch/en/newnsb/B7r1ty-ihMFGnJMtU9xZO",
  "publishTime": "2025-10-16T20:35:58.980917+00:00",
  "category": "government",
  "language": "en",
  "extractedAt": "2025-10-16T20:35:58.980918+00:00",
  "extractedBy": "github-pages-crawler"
}