{
  "id": "瑞士联邦政府_6_1763720185",
  "title": "More about «How the cheese-noodle principle could help counter Alzheimer's»",
  "titleChinese": "More about «How the cheese-noodle principle could help counter Alzheimer's»",
  "source": "瑞士联邦政府",
  "url": "https://www.admin.ch/en/newnsb/fBAo17V92-t17SDdlIITv",
  "publishTime": "2025-11-21T10:16:25.043967+00:00",
  "category": "government",
  "language": "en",
  "extractedAt": "2025-11-21T10:16:25.043969+00:00",
  "extractedBy": "github-pages-crawler"
}