{
  "id": "瑞士联邦政府_12_1774983296",
  "title": "More about «State Secretary Hirayama attends informal EU ministerial meeting on competition in research and innovation»",
  "titleChinese": "More about «State Secretary Hirayama attends informal EU ministerial meeting on competition in research and innovation»",
  "source": "瑞士联邦政府",
  "url": "https://www.admin.ch/en/newnsb/CTSabqPJhTIfzWjSu6BeO",
  "publishTime": "2026-03-31T18:54:56.518290+00:00",
  "category": "government",
  "language": "en",
  "extractedAt": "2026-03-31T18:54:56.518292+00:00",
  "extractedBy": "github-pages-crawler"
}