{
  "id": "瑞士联邦政府_10_1764731608",
  "title": "More about «Address by Federal Councillor Martin Pfister at Swiss Defence Industry Day»",
  "titleChinese": "More about «Address by Federal Councillor Martin Pfister at Swiss Defence Industry Day»",
  "source": "瑞士联邦政府",
  "url": "https://www.admin.ch/en/newnsb/4G-qUoSDizhuGrZXLdT_U",
  "publishTime": "2025-12-03T03:13:28.032936+00:00",
  "category": "government",
  "language": "en",
  "extractedAt": "2025-12-03T03:13:28.032938+00:00",
  "extractedBy": "github-pages-crawler"
}