{
  "id": "瑞士联邦政府_8_1764252941",
  "title": "More about «Employment driven by Swiss enterprise groups, turnover by foreign multinationals»",
  "titleChinese": "More about «Employment driven by Swiss enterprise groups, turnover by foreign multinationals»",
  "source": "瑞士联邦政府",
  "url": "https://www.admin.ch/en/newnsb/JYypuIwYkeNto03DLe3Sm",
  "publishTime": "2025-11-27T14:15:41.945948+00:00",
  "category": "government",
  "language": "en",
  "extractedAt": "2025-11-27T14:15:41.945950+00:00",
  "extractedBy": "github-pages-crawler"
}