{
  "id": "瑞士联邦政府_10_1762244459",
  "title": "More about «80 years of UNESCO: tackling global challenges related to new technologies (FR)»",
  "titleChinese": "More about «80 years of UNESCO: tackling global challenges related to new technologies (FR)»",
  "source": "瑞士联邦政府",
  "url": "https://www.admin.ch/en/newnsb/D97ePO8Fk3fmXbZcwDHS3",
  "publishTime": "2025-11-04T08:20:59.668928+00:00",
  "category": "government",
  "language": "en",
  "extractedAt": "2025-11-04T08:20:59.668929+00:00",
  "extractedBy": "github-pages-crawler"
}