{
  "id": "瑞士联邦政府_9_1763954386",
  "title": "More about «State Secretary Mäder attends Halifax International Security Forum»",
  "titleChinese": "More about «State Secretary Mäder attends Halifax International Security Forum»",
  "source": "瑞士联邦政府",
  "url": "https://www.admin.ch/en/newnsb/nuOia486OhE7kwXQMjLa4",
  "publishTime": "2025-11-24T03:19:46.325018+00:00",
  "category": "government",
  "language": "en",
  "extractedAt": "2025-11-24T03:19:46.325020+00:00",
  "extractedBy": "github-pages-crawler"
}