{
  "id": "瑞士联邦政府_8_1761029450",
  "title": "More about «SDG Flag Day in Lugano: first dialogue between some of Switzerland's largest cities»",
  "titleChinese": "More about «SDG Flag Day in Lugano: first dialogue between some of Switzerland's largest cities»",
  "source": "瑞士联邦政府",
  "url": "https://www.admin.ch/en/newnsb/pOA8PcsZQA3KQsAh5Jnvm",
  "publishTime": "2025-10-21T06:50:50.829803+00:00",
  "category": "government",
  "language": "en",
  "extractedAt": "2025-10-21T06:50:50.829805+00:00",
  "extractedBy": "github-pages-crawler"
}