{
  "id": "瑞士联邦政府_11_1761827440",
  "title": "More about «Residential property prices increased by 0.8% in 3rd quarter 2025»",
  "titleChinese": "More about «Residential property prices increased by 0.8% in 3rd quarter 2025»",
  "source": "瑞士联邦政府",
  "url": "https://www.admin.ch/en/newnsb/EQpGjlu3jzUbrgtFFGaq8",
  "publishTime": "2025-10-30T12:30:40.129839+00:00",
  "category": "government",
  "language": "en",
  "extractedAt": "2025-10-30T12:30:40.129841+00:00",
  "extractedBy": "github-pages-crawler"
}