{
  "id": "瑞士联邦政府_14_1771120191",
  "title": "More about «Federal Councillors Martin Pfister, Ignazio Cassis and Beat Jans to attend the Munich Security Conference»",
  "titleChinese": "More about «Federal Councillors Martin Pfister, Ignazio Cassis and Beat Jans to attend the Munich Security Conference»",
  "source": "瑞士联邦政府",
  "url": "https://www.admin.ch/en/newnsb/ztc4zjj7Ys96l8JXvUjDK",
  "publishTime": "2026-02-15T01:49:51.583565+00:00",
  "category": "government",
  "language": "en",
  "extractedAt": "2026-02-15T01:49:51.583567+00:00",
  "extractedBy": "github-pages-crawler"
}