{
  "id": "瑞士联邦政府_7_1772282062",
  "title": "More about «Major General Patrick Gauchat concludes successful assignment as Head of UNTSO»",
  "titleChinese": "More about «Major General Patrick Gauchat concludes successful assignment as Head of UNTSO»",
  "source": "瑞士联邦政府",
  "url": "https://www.admin.ch/en/newnsb/MrMqiHRpUI14",
  "publishTime": "2026-02-28T12:34:22.011337+00:00",
  "category": "government",
  "language": "en",
  "extractedAt": "2026-02-28T12:34:22.011339+00:00",
  "extractedBy": "github-pages-crawler"
}