{
  "id": "瑞士联邦政府_7_1761054297",
  "title": "More about «Sanctions: Ordinance on measures against the Islamic Republic of Iran»",
  "titleChinese": "More about «Sanctions: Ordinance on measures against the Islamic Republic of Iran»",
  "source": "瑞士联邦政府",
  "url": "https://www.admin.ch/en/newnsb/WLmQvhZ6BthAOXwTU2bwy",
  "publishTime": "2025-10-21T13:44:57.968588+00:00",
  "category": "government",
  "language": "en",
  "extractedAt": "2025-10-21T13:44:57.968590+00:00",
  "extractedBy": "github-pages-crawler"
}