{
  "id": "瑞士联邦政府_7_1768242329",
  "title": "More about «Nomination procedure launched for Marcel Benoist Swiss Science Prize»",
  "titleChinese": "More about «Nomination procedure launched for Marcel Benoist Swiss Science Prize»",
  "source": "瑞士联邦政府",
  "url": "https://www.admin.ch/en/newnsb/DGRVVjPCdwe7q8BsmnB3m",
  "publishTime": "2026-01-12T18:25:29.318117+00:00",
  "category": "government",
  "language": "en",
  "extractedAt": "2026-01-12T18:25:29.318120+00:00",
  "extractedBy": "github-pages-crawler"
}