{
  "id": "瑞士联邦政府_12_1765225072",
  "title": "More about «Entry into force of thethe double taxation agreement with Jordan»",
  "titleChinese": "More about «Entry into force of thethe double taxation agreement with Jordan»",
  "source": "瑞士联邦政府",
  "url": "https://www.admin.ch/en/newnsb/fCu81zLNbhMbUcx2ZzWfS",
  "publishTime": "2025-12-08T20:17:52.387342+00:00",
  "category": "government",
  "language": "en",
  "extractedAt": "2025-12-08T20:17:52.387344+00:00",
  "extractedBy": "github-pages-crawler"
}