{
  "id": "瑞士联邦政府_13_1764318097",
  "title": "More about «Federal Council decides on activation of safeguard clause with regard to Croatia»",
  "titleChinese": "More about «Federal Council decides on activation of safeguard clause with regard to Croatia»",
  "source": "瑞士联邦政府",
  "url": "https://www.admin.ch/en/newnsb/s5sFVBASZzom",
  "publishTime": "2025-11-28T08:21:37.815247+00:00",
  "category": "government",
  "language": "en",
  "extractedAt": "2025-11-28T08:21:37.815249+00:00",
  "extractedBy": "github-pages-crawler"
}