{
  "id": "瑞士联邦政府_11_1773752378",
  "title": "More about «SDC steps up humanitarian support for people in Lebanon, Syria and Iran»",
  "titleChinese": "More about «SDC steps up humanitarian support for people in Lebanon, Syria and Iran»",
  "source": "瑞士联邦政府",
  "url": "https://www.admin.ch/en/newnsb/V-OEiZFDCNXDa_WIWDpWZ",
  "publishTime": "2026-03-17T12:59:38.485291+00:00",
  "category": "government",
  "language": "en",
  "extractedAt": "2026-03-17T12:59:38.485292+00:00",
  "extractedBy": "github-pages-crawler"
}