{
  "id": "瑞士联邦政府_8_1763806481",
  "title": "More about «Switzerland and the United Kingdom discuss science and innovation»",
  "titleChinese": "More about «Switzerland and the United Kingdom discuss science and innovation»",
  "source": "瑞士联邦政府",
  "url": "https://www.admin.ch/en/newnsb/UQuA_HwdndaZzJdMVZf0u",
  "publishTime": "2025-11-22T10:14:41.353224+00:00",
  "category": "government",
  "language": "en",
  "extractedAt": "2025-11-22T10:14:41.353226+00:00",
  "extractedBy": "github-pages-crawler"
}