{
  "lastUpdated": "2025-10-30T03:07:25.607928+00:00",
  "count": 10,
  "news": [
    {
      "id": "瑞士联邦政府_13_1761793642",
      "title": "More about «Empa's research in space: “We need a certain critical mass”»",
      "titleChinese": "More about «Empa's research in space: “We need a certain critical mass”»",
      "source": "瑞士联邦政府",
      "url": "https://www.admin.ch/en/newnsb/tEkyb53XN7QNSfe95qvWj",
      "publishTime": "2025-10-30T03:07:22.805050+00:00",
      "category": "government",
      "language": "en",
      "extractedAt": "2025-10-30T03:07:22.805051+00:00",
      "extractedBy": "github-pages-crawler"
    },
    {
      "id": "瑞士联邦政府_12_1761793642",
      "title": "More about «Switzerland – United Kingdom: Extension of the agreement on the mobility of service suppliers»",
      "titleChinese": "More about «Switzerland – United Kingdom: Extension of the agreement on the mobility of service suppliers»",
      "source": "瑞士联邦政府",
      "url": "https://www.admin.ch/en/newnsb/-oGV4OhAEI64WEyF8loIH",
      "publishTime": "2025-10-30T03:07:22.805039+00:00",
      "category": "government",
      "language": "en",
      "extractedAt": "2025-10-30T03:07:22.805040+00:00",
      "extractedBy": "github-pages-crawler"
    },
    {
      "id": "瑞士联邦政府_11_1761793642",
      "title": "More about «Continued support for weapons and ammunition management training in Bosnia and Herzegovina»",
      "titleChinese": "More about «Continued support for weapons and ammunition management training in Bosnia and Herzegovina»",
      "source": "瑞士联邦政府",
      "url": "https://www.admin.ch/en/newnsb/pyGcVzQ1w8inTl1aeHiAW",
      "publishTime": "2025-10-30T03:07:22.805028+00:00",
      "category": "government",
      "language": "en",
      "extractedAt": "2025-10-30T03:07:22.805030+00:00",
      "extractedBy": "github-pages-crawler"
    },
    {
      "id": "瑞士联邦政府_10_1761793642",
      "title": "More about «Switzerland updates administrative arrangement with the European Defence Agency»",
      "titleChinese": "More about «Switzerland updates administrative arrangement with the European Defence Agency»",
      "source": "瑞士联邦政府",
      "url": "https://www.admin.ch/en/newnsb/jqeY1_dgJyb3wlQ2pZqUs",
      "publishTime": "2025-10-30T03:07:22.805020+00:00",
      "category": "government",
      "language": "en",
      "extractedAt": "2025-10-30T03:07:22.805022+00:00",
      "extractedBy": "github-pages-crawler"
    },
    {
      "id": "瑞士联邦政府_9_1761793642",
      "title": "More about «Second 2025 extrapolation confirms financing deficit»",
      "titleChinese": "More about «Second 2025 extrapolation confirms financing deficit»",
      "source": "瑞士联邦政府",
      "url": "https://www.admin.ch/en/newnsb/q6YybPQQwFB0fJCzSUP9o",
      "publishTime": "2025-10-30T03:07:22.805012+00:00",
      "category": "government",
      "language": "en",
      "extractedAt": "2025-10-30T03:07:22.805014+00:00",
      "extractedBy": "github-pages-crawler"
    },
    {
      "id": "瑞士联邦政府_8_1761793642",
      "title": "More about «New law on communication platforms and search engines: Start of consultation proceedings»",
      "titleChinese": "More about «New law on communication platforms and search engines: Start of consultation proceedings»",
      "source": "瑞士联邦政府",
      "url": "https://www.admin.ch/en/newnsb/6TmEAde4htulaWG9CWYtK",
      "publishTime": "2025-10-30T03:07:22.805004+00:00",
      "category": "government",
      "language": "en",
      "extractedAt": "2025-10-30T03:07:22.805006+00:00",
      "extractedBy": "github-pages-crawler"
    },
    {
      "id": "瑞士联邦政府_7_1761793642",
      "title": "More about «State visit by President Cyril Ramaphosa: Switzerland and South Africa strengthen relations»",
      "titleChinese": "More about «State visit by President Cyril Ramaphosa: Switzerland and South Africa strengthen relations»",
      "source": "瑞士联邦政府",
      "url": "https://www.admin.ch/en/newnsb/jV4-v3Ni8VVZsaylBsQNE",
      "publishTime": "2025-10-30T03:07:22.804994+00:00",
      "category": "government",
      "language": "en",
      "extractedAt": "2025-10-30T03:07:22.804996+00:00",
      "extractedBy": "github-pages-crawler"
    },
    {
      "id": "瑞士联邦政府_6_1761793642",
      "title": "More about «Ukraine: Federal Council applies 18th EU sanctions package»",
      "titleChinese": "More about «Ukraine: Federal Council applies 18th EU sanctions package»",
      "source": "瑞士联邦政府",
      "url": "https://www.admin.ch/en/newnsb/kdsi2Frn5Y-xc9mE46C8C",
      "publishTime": "2025-10-30T03:07:22.804981+00:00",
      "category": "government",
      "language": "en",
      "extractedAt": "2025-10-30T03:07:22.804983+00:00",
      "extractedBy": "github-pages-crawler"
    },
    {
      "id": "瑞士联邦政府_1_1761793642",
      "title": "News Service BundNews Service BundThe portal of the Swiss government",
      "titleChinese": "News Service BundNews Service BundThe portal of the Swiss government",
      "source": "瑞士联邦政府",
      "url": "https://www.admin.ch/en",
      "publishTime": "2025-10-30T03:07:22.804955+00:00",
      "category": "government",
      "language": "en",
      "extractedAt": "2025-10-30T03:07:22.804958+00:00",
      "extractedBy": "github-pages-crawler"
    },
    {
      "id": "瑞士联邦政府_0_1761793642",
      "title": "Skip to main content",
      "titleChinese": "Skip to main content",
      "source": "瑞士联邦政府",
      "url": "https://www.admin.ch#main-content",
      "publishTime": "2025-10-30T03:07:22.804906+00:00",
      "category": "government",
      "language": "en",
      "extractedAt": "2025-10-30T03:07:22.804922+00:00",
      "extractedBy": "github-pages-crawler"
    }
  ]
}