{
  "lastUpdated": "2025-12-09T14:17:22.290729+00:00",
  "count": 10,
  "news": [
    {
      "id": "瑞士联邦政府_13_1765289840",
      "title": "More about «Consumer sentiment higher than a year ago»",
      "titleChinese": "More about «Consumer sentiment higher than a year ago»",
      "source": "瑞士联邦政府",
      "url": "https://www.admin.ch/en/newnsb/SE79ADEBL3hcauaVperQX",
      "publishTime": "2025-12-09T14:17:20.007443+00:00",
      "category": "government",
      "language": "en",
      "extractedAt": "2025-12-09T14:17:20.007444+00:00",
      "extractedBy": "github-pages-crawler"
    },
    {
      "id": "瑞士联邦政府_12_1765289840",
      "title": "More about «Optimising the treatment of eye tumours»",
      "titleChinese": "More about «Optimising the treatment of eye tumours»",
      "source": "瑞士联邦政府",
      "url": "https://www.admin.ch/en/newnsb/_ag7S5OCngcg_kV6XUqBp",
      "publishTime": "2025-12-09T14:17:20.007435+00:00",
      "category": "government",
      "language": "en",
      "extractedAt": "2025-12-09T14:17:20.007437+00:00",
      "extractedBy": "github-pages-crawler"
    },
    {
      "id": "瑞士联邦政府_11_1765289840",
      "title": "More about «Programme of Switzerland's OSCE chairpersonship in 2026»",
      "titleChinese": "More about «Programme of Switzerland's OSCE chairpersonship in 2026»",
      "source": "瑞士联邦政府",
      "url": "https://www.admin.ch/en/newnsb/l4w4KY6jBm0syJJiDiH3R",
      "publishTime": "2025-12-09T14:17:20.007427+00:00",
      "category": "government",
      "language": "en",
      "extractedAt": "2025-12-09T14:17:20.007429+00:00",
      "extractedBy": "github-pages-crawler"
    },
    {
      "id": "瑞士联邦政府_10_1765289840",
      "title": "More about «RailCom dismisses appeal against TVS ruling»",
      "titleChinese": "More about «RailCom dismisses appeal against TVS ruling»",
      "source": "瑞士联邦政府",
      "url": "https://www.admin.ch/en/newnsb/XiRJQSg4NBzU",
      "publishTime": "2025-12-09T14:17:20.007412+00:00",
      "category": "government",
      "language": "en",
      "extractedAt": "2025-12-09T14:17:20.007415+00:00",
      "extractedBy": "github-pages-crawler"
    },
    {
      "id": "瑞士联邦政府_9_1765289840",
      "title": "More about «New Confederation bond»",
      "titleChinese": "More about «New Confederation bond»",
      "source": "瑞士联邦政府",
      "url": "https://www.admin.ch/en/newnsb/ze-QWiRDZNOGIFN-Elkzz",
      "publishTime": "2025-12-09T14:17:20.007354+00:00",
      "category": "government",
      "language": "en",
      "extractedAt": "2025-12-09T14:17:20.007356+00:00",
      "extractedBy": "github-pages-crawler"
    },
    {
      "id": "瑞士联邦政府_8_1765289840",
      "title": "More about «Turnover and employment in Swiss market sector activities fell in 3rd quarter 2025»",
      "titleChinese": "More about «Turnover and employment in Swiss market sector activities fell in 3rd quarter 2025»",
      "source": "瑞士联邦政府",
      "url": "https://www.admin.ch/en/newnsb/gnPDjWOFrBuAau_hpf_WC",
      "publishTime": "2025-12-09T14:17:20.007345+00:00",
      "category": "government",
      "language": "en",
      "extractedAt": "2025-12-09T14:17:20.007347+00:00",
      "extractedBy": "github-pages-crawler"
    },
    {
      "id": "瑞士联邦政府_7_1765289840",
      "title": "More about «ICOS Cities project completed: Novel approaches for determining a city‘s CO₂ emissions»",
      "titleChinese": "More about «ICOS Cities project completed: Novel approaches for determining a city‘s CO₂ emissions»",
      "source": "瑞士联邦政府",
      "url": "https://www.admin.ch/en/newnsb/1tYgH-B_xrtcP6lUcvtNt",
      "publishTime": "2025-12-09T14:17:20.007336+00:00",
      "category": "government",
      "language": "en",
      "extractedAt": "2025-12-09T14:17:20.007338+00:00",
      "extractedBy": "github-pages-crawler"
    },
    {
      "id": "瑞士联邦政府_6_1765289840",
      "title": "More about «SECO: Ordinance instituting measures in relation to Sudan»",
      "titleChinese": "More about «SECO: Ordinance instituting measures in relation to Sudan»",
      "source": "瑞士联邦政府",
      "url": "https://www.admin.ch/en/newnsb/7liEudkw7fn0m5WpxZ30N",
      "publishTime": "2025-12-09T14:17:20.007322+00:00",
      "category": "government",
      "language": "en",
      "extractedAt": "2025-12-09T14:17:20.007324+00:00",
      "extractedBy": "github-pages-crawler"
    },
    {
      "id": "瑞士联邦政府_1_1765289840",
      "title": "News Service BundNews Service BundThe portal of the Swiss government",
      "titleChinese": "News Service BundNews Service BundThe portal of the Swiss government",
      "source": "瑞士联邦政府",
      "url": "https://www.admin.ch/en",
      "publishTime": "2025-12-09T14:17:20.007297+00:00",
      "category": "government",
      "language": "en",
      "extractedAt": "2025-12-09T14:17:20.007299+00:00",
      "extractedBy": "github-pages-crawler"
    },
    {
      "id": "瑞士联邦政府_0_1765289840",
      "title": "Skip to main content",
      "titleChinese": "Skip to main content",
      "source": "瑞士联邦政府",
      "url": "https://www.admin.ch#main-content",
      "publishTime": "2025-12-09T14:17:20.007261+00:00",
      "category": "government",
      "language": "en",
      "extractedAt": "2025-12-09T14:17:20.007280+00:00",
      "extractedBy": "github-pages-crawler"
    }
  ]
}