{
  "lastUpdated": "2026-04-06T09:02:48.723730+00:00",
  "count": 10,
  "news": [
    {
      "id": "瑞士联邦政府_14_1775466166",
      "title": "More about «Switzerland seen from abroad in 2025: excellent reputation among the public; response to US tariffs in the media spotlight»",
      "titleChinese": "More about «Switzerland seen from abroad in 2025: excellent reputation among the public; response to US tariffs in the media spotlight»",
      "source": "瑞士联邦政府",
      "url": "https://www.admin.ch/en/newnsb/Jn6_Yz-bNwWClc3nZe-Qb",
      "publishTime": "2026-04-06T09:02:46.348898+00:00",
      "category": "government",
      "language": "en",
      "extractedAt": "2026-04-06T09:02:46.348899+00:00",
      "extractedBy": "github-pages-crawler"
    },
    {
      "id": "瑞士联邦政府_13_1775466166",
      "title": "More about «SECO: Ordinance on Measures Relating to the Situation in Ukraine»",
      "titleChinese": "More about «SECO: Ordinance on Measures Relating to the Situation in Ukraine»",
      "source": "瑞士联邦政府",
      "url": "https://www.admin.ch/en/newnsb/Y-YJTQOpyuTVM1aqSuI4T",
      "publishTime": "2026-04-06T09:02:46.348890+00:00",
      "category": "government",
      "language": "en",
      "extractedAt": "2026-04-06T09:02:46.348892+00:00",
      "extractedBy": "github-pages-crawler"
    },
    {
      "id": "瑞士联邦政府_12_1775466166",
      "title": "More about «Consumer prices increased by 0.2% in March»",
      "titleChinese": "More about «Consumer prices increased by 0.2% in March»",
      "source": "瑞士联邦政府",
      "url": "https://www.admin.ch/en/newnsb/oZkj7wiuTUY5GZly6E38h",
      "publishTime": "2026-04-06T09:02:46.348883+00:00",
      "category": "government",
      "language": "en",
      "extractedAt": "2026-04-06T09:02:46.348884+00:00",
      "extractedBy": "github-pages-crawler"
    },
    {
      "id": "瑞士联邦政府_11_1775466166",
      "title": "More about «Switzerland’s demographic ageing progressed in 2025»",
      "titleChinese": "More about «Switzerland’s demographic ageing progressed in 2025»",
      "source": "瑞士联邦政府",
      "url": "https://www.admin.ch/en/newnsb/acGCTisDEW60tUk1jSz4Z",
      "publishTime": "2026-04-06T09:02:46.348875+00:00",
      "category": "government",
      "language": "en",
      "extractedAt": "2026-04-06T09:02:46.348877+00:00",
      "extractedBy": "github-pages-crawler"
    },
    {
      "id": "瑞士联邦政府_10_1775466166",
      "title": "More about «New STSB final report (aviation) available»",
      "titleChinese": "More about «New STSB final report (aviation) available»",
      "source": "瑞士联邦政府",
      "url": "https://www.admin.ch/en/newnsb/ymX9lJsg-5ZWi5euVcD8k",
      "publishTime": "2026-04-06T09:02:46.348863+00:00",
      "category": "government",
      "language": "en",
      "extractedAt": "2026-04-06T09:02:46.348865+00:00",
      "extractedBy": "github-pages-crawler"
    },
    {
      "id": "瑞士联邦政府_9_1775466166",
      "title": "More about «Prevention bulletin 2025/4 aviation»",
      "titleChinese": "More about «Prevention bulletin 2025/4 aviation»",
      "source": "瑞士联邦政府",
      "url": "https://www.admin.ch/en/newnsb/UyFk_N7kysz7Jq9wB4_yu",
      "publishTime": "2026-04-06T09:02:46.348855+00:00",
      "category": "government",
      "language": "en",
      "extractedAt": "2026-04-06T09:02:46.348857+00:00",
      "extractedBy": "github-pages-crawler"
    },
    {
      "id": "瑞士联邦政府_8_1775466166",
      "title": "More about «Office of the Attorney General of Switzerland delivers significant outcomes in 2025 and contributes to reinforced internal security»",
      "titleChinese": "More about «Office of the Attorney General of Switzerland delivers significant outcomes in 2025 and contributes to reinforced internal security»",
      "source": "瑞士联邦政府",
      "url": "https://www.admin.ch/en/newnsb/HXKYFESgffYvQOzpHDVOB",
      "publishTime": "2026-04-06T09:02:46.348847+00:00",
      "category": "government",
      "language": "en",
      "extractedAt": "2026-04-06T09:02:46.348848+00:00",
      "extractedBy": "github-pages-crawler"
    },
    {
      "id": "瑞士联邦政府_7_1775466166",
      "title": "More about «Ignazio Cassis and Beat Jans meet with Algerian foreign minister, Ahmed Attaf»",
      "titleChinese": "More about «Ignazio Cassis and Beat Jans meet with Algerian foreign minister, Ahmed Attaf»",
      "source": "瑞士联邦政府",
      "url": "https://www.admin.ch/en/newnsb/Mc2sF60myBkTAC8W5H4iu",
      "publishTime": "2026-04-06T09:02:46.348837+00:00",
      "category": "government",
      "language": "en",
      "extractedAt": "2026-04-06T09:02:46.348839+00:00",
      "extractedBy": "github-pages-crawler"
    },
    {
      "id": "瑞士联邦政府_1_1775466166",
      "title": "News Service BundNews Service BundThe portal of the Swiss government",
      "titleChinese": "News Service BundNews Service BundThe portal of the Swiss government",
      "source": "瑞士联邦政府",
      "url": "https://www.admin.ch/en",
      "publishTime": "2026-04-06T09:02:46.348804+00:00",
      "category": "government",
      "language": "en",
      "extractedAt": "2026-04-06T09:02:46.348806+00:00",
      "extractedBy": "github-pages-crawler"
    },
    {
      "id": "瑞士联邦政府_0_1775466166",
      "title": "Skip to main content",
      "titleChinese": "Skip to main content",
      "source": "瑞士联邦政府",
      "url": "https://www.admin.ch#main-content",
      "publishTime": "2026-04-06T09:02:46.348759+00:00",
      "category": "government",
      "language": "en",
      "extractedAt": "2026-04-06T09:02:46.348787+00:00",
      "extractedBy": "github-pages-crawler"
    }
  ]
}