{
  "lastUpdated": "2025-12-19T03:19:53.743023+00:00",
  "count": 10,
  "news": [
    {
      "id": "瑞士联邦政府_13_1766114391",
      "title": "More about «Switzerland signs Convention establishing International Claims Commission for Ukraine»",
      "titleChinese": "More about «Switzerland signs Convention establishing International Claims Commission for Ukraine»",
      "source": "瑞士联邦政府",
      "url": "https://www.admin.ch/en/newnsb/KL-GQII6C6BDh2ENuTGGw",
      "publishTime": "2025-12-19T03:19:51.470208+00:00",
      "category": "government",
      "language": "en",
      "extractedAt": "2025-12-19T03:19:51.470210+00:00",
      "extractedBy": "github-pages-crawler"
    },
    {
      "id": "瑞士联邦政府_12_1766114391",
      "title": "More about «New STSB final report (cable car) available»",
      "titleChinese": "More about «New STSB final report (cable car) available»",
      "source": "瑞士联邦政府",
      "url": "https://www.admin.ch/en/newnsb/Wu76urz4ogxdpMml7fIEF",
      "publishTime": "2025-12-19T03:19:51.470199+00:00",
      "category": "government",
      "language": "en",
      "extractedAt": "2025-12-19T03:19:51.470201+00:00",
      "extractedBy": "github-pages-crawler"
    },
    {
      "id": "瑞士联邦政府_11_1766114391",
      "title": "More about «Taskforce Drones tests the technological maturity of attack and defence drones»",
      "titleChinese": "More about «Taskforce Drones tests the technological maturity of attack and defence drones»",
      "source": "瑞士联邦政府",
      "url": "https://www.admin.ch/en/newnsb/yxSch-tc_pUdgaHa_UL07",
      "publishTime": "2025-12-19T03:19:51.470189+00:00",
      "category": "government",
      "language": "en",
      "extractedAt": "2025-12-19T03:19:51.470192+00:00",
      "extractedBy": "github-pages-crawler"
    },
    {
      "id": "瑞士联邦政府_10_1766114391",
      "title": "More about «COMCO Closes Chapter on Financial Market Investigations»",
      "titleChinese": "More about «COMCO Closes Chapter on Financial Market Investigations»",
      "source": "瑞士联邦政府",
      "url": "https://www.admin.ch/en/newnsb/GmkisOCZfpqxWbOawM4wL",
      "publishTime": "2025-12-19T03:19:51.470179+00:00",
      "category": "government",
      "language": "en",
      "extractedAt": "2025-12-19T03:19:51.470181+00:00",
      "extractedBy": "github-pages-crawler"
    },
    {
      "id": "瑞士联邦政府_9_1766114391",
      "title": "More about «Construction prices rose by 0.3% in October 2025»",
      "titleChinese": "More about «Construction prices rose by 0.3% in October 2025»",
      "source": "瑞士联邦政府",
      "url": "https://www.admin.ch/en/newnsb/LZsZNzuQcm64aatATMsJd",
      "publishTime": "2025-12-19T03:19:51.470170+00:00",
      "category": "government",
      "language": "en",
      "extractedAt": "2025-12-19T03:19:51.470172+00:00",
      "extractedBy": "github-pages-crawler"
    },
    {
      "id": "瑞士联邦政府_8_1766114391",
      "title": "More about «Switzerland welcomes UN commitment to inclusive digital governance»",
      "titleChinese": "More about «Switzerland welcomes UN commitment to inclusive digital governance»",
      "source": "瑞士联邦政府",
      "url": "https://www.admin.ch/en/newnsb/CAElCNKgCFRC42v0VIBYB",
      "publishTime": "2025-12-19T03:19:51.470158+00:00",
      "category": "government",
      "language": "en",
      "extractedAt": "2025-12-19T03:19:51.470160+00:00",
      "extractedBy": "github-pages-crawler"
    },
    {
      "id": "瑞士联邦政府_7_1766114391",
      "title": "More about «Switzerland concludes two new status agreements with organisations active in International Geneva»",
      "titleChinese": "More about «Switzerland concludes two new status agreements with organisations active in International Geneva»",
      "source": "瑞士联邦政府",
      "url": "https://www.admin.ch/en/newnsb/ExtufOh_RyVN9Xm4EQiYB",
      "publishTime": "2025-12-19T03:19:51.470144+00:00",
      "category": "government",
      "language": "en",
      "extractedAt": "2025-12-19T03:19:51.470146+00:00",
      "extractedBy": "github-pages-crawler"
    },
    {
      "id": "瑞士联邦政府_6_1766114391",
      "title": "More about «Cooperation between Switzerland and NATO: The objectives defined for the period from 2025 to 2028»",
      "titleChinese": "More about «Cooperation between Switzerland and NATO: The objectives defined for the period from 2025 to 2028»",
      "source": "瑞士联邦政府",
      "url": "https://www.admin.ch/en/newnsb/StKnoep8yxplsAK6xeHfo",
      "publishTime": "2025-12-19T03:19:51.470130+00:00",
      "category": "government",
      "language": "en",
      "extractedAt": "2025-12-19T03:19:51.470132+00:00",
      "extractedBy": "github-pages-crawler"
    },
    {
      "id": "瑞士联邦政府_1_1766114391",
      "title": "News Service BundNews Service BundThe portal of the Swiss government",
      "titleChinese": "News Service BundNews Service BundThe portal of the Swiss government",
      "source": "瑞士联邦政府",
      "url": "https://www.admin.ch/en",
      "publishTime": "2025-12-19T03:19:51.470105+00:00",
      "category": "government",
      "language": "en",
      "extractedAt": "2025-12-19T03:19:51.470107+00:00",
      "extractedBy": "github-pages-crawler"
    },
    {
      "id": "瑞士联邦政府_0_1766114391",
      "title": "Skip to main content",
      "titleChinese": "Skip to main content",
      "source": "瑞士联邦政府",
      "url": "https://www.admin.ch#main-content",
      "publishTime": "2025-12-19T03:19:51.470070+00:00",
      "category": "government",
      "language": "en",
      "extractedAt": "2025-12-19T03:19:51.470087+00:00",
      "extractedBy": "github-pages-crawler"
    }
  ]
}