{
  "lastUpdated": "2025-12-08T08:24:33.218792+00:00",
  "totalCount": 10,
  "version": "1.0.0",
  "source": "GitHub Pages Crawler",
  "news": [
    {
      "id": "瑞士联邦政府_13_1765182271",
      "title": "More about «Federal Council appoints Daniel Frutig-Meier as chairman of the Board of Directors of RUAG International»",
      "titleChinese": "More about «Federal Council appoints Daniel Frutig-Meier as chairman of the Board of Directors of RUAG International»",
      "source": "瑞士联邦政府",
      "url": "https://www.admin.ch/en/newnsb/1SPdOzJNFw1Fn9b2YSgor",
      "publishTime": "2025-12-08T08:24:31.056592+00:00",
      "category": "government",
      "language": "en",
      "extractedAt": "2025-12-08T08:24:31.056593+00:00",
      "extractedBy": "github-pages-crawler"
    },
    {
      "id": "瑞士联邦政府_12_1765182271",
      "title": "More about «Draft negotiating mandate for a trade agreement with the USA»",
      "titleChinese": "More about «Draft negotiating mandate for a trade agreement with the USA»",
      "source": "瑞士联邦政府",
      "url": "https://www.admin.ch/en/newnsb/HdHW8zPFrf2i30cJfRzFC",
      "publishTime": "2025-12-08T08:24:31.056584+00:00",
      "category": "government",
      "language": "en",
      "extractedAt": "2025-12-08T08:24:31.056585+00:00",
      "extractedBy": "github-pages-crawler"
    },
    {
      "id": "瑞士联邦政府_11_1765182271",
      "title": "More about «Result of consultation: clear majority for Swiss–EU package»",
      "titleChinese": "More about «Result of consultation: clear majority for Swiss–EU package»",
      "source": "瑞士联邦政府",
      "url": "https://www.admin.ch/en/newnsb/uqY0xLewZcLuWCd2H4p_K",
      "publishTime": "2025-12-08T08:24:31.056574+00:00",
      "category": "government",
      "language": "en",
      "extractedAt": "2025-12-08T08:24:31.056577+00:00",
      "extractedBy": "github-pages-crawler"
    },
    {
      "id": "瑞士联邦政府_10_1765182271",
      "title": "More about «Entry into force of thethe double taxation agreement with Jordan»",
      "titleChinese": "More about «Entry into force of thethe double taxation agreement with Jordan»",
      "source": "瑞士联邦政府",
      "url": "https://www.admin.ch/en/newnsb/fCu81zLNbhMbUcx2ZzWfS",
      "publishTime": "2025-12-08T08:24:31.056566+00:00",
      "category": "government",
      "language": "en",
      "extractedAt": "2025-12-08T08:24:31.056567+00:00",
      "extractedBy": "github-pages-crawler"
    },
    {
      "id": "瑞士联邦政府_9_1765182271",
      "title": "More about «Home moves remain at a record low»",
      "titleChinese": "More about «Home moves remain at a record low»",
      "source": "瑞士联邦政府",
      "url": "https://www.admin.ch/en/newnsb/00Sgnb5SWFLSAIQ4mCbGS",
      "publishTime": "2025-12-08T08:24:31.056555+00:00",
      "category": "government",
      "language": "en",
      "extractedAt": "2025-12-08T08:24:31.056556+00:00",
      "extractedBy": "github-pages-crawler"
    },
    {
      "id": "瑞士联邦政府_8_1765182271",
      "title": "More about «Record number of overnight stays in Swiss hotel sector for third consecutive year in 2025 summer season»",
      "titleChinese": "More about «Record number of overnight stays in Swiss hotel sector for third consecutive year in 2025 summer season»",
      "source": "瑞士联邦政府",
      "url": "https://www.admin.ch/en/newnsb/TtduwrT9Od0FbyD4e7irP",
      "publishTime": "2025-12-08T08:24:31.056546+00:00",
      "category": "government",
      "language": "en",
      "extractedAt": "2025-12-08T08:24:31.056548+00:00",
      "extractedBy": "github-pages-crawler"
    },
    {
      "id": "瑞士联邦政府_7_1765182271",
      "title": "More about «Consumer sentiment higher than a year ago»",
      "titleChinese": "More about «Consumer sentiment higher than a year ago»",
      "source": "瑞士联邦政府",
      "url": "https://www.admin.ch/en/newnsb/SE79ADEBL3hcauaVperQX",
      "publishTime": "2025-12-08T08:24:31.056536+00:00",
      "category": "government",
      "language": "en",
      "extractedAt": "2025-12-08T08:24:31.056538+00:00",
      "extractedBy": "github-pages-crawler"
    },
    {
      "id": "瑞士联邦政府_6_1765182271",
      "title": "More about «Optimising the treatment of eye tumours»",
      "titleChinese": "More about «Optimising the treatment of eye tumours»",
      "source": "瑞士联邦政府",
      "url": "https://www.admin.ch/en/newnsb/_ag7S5OCngcg_kV6XUqBp",
      "publishTime": "2025-12-08T08:24:31.056523+00:00",
      "category": "government",
      "language": "en",
      "extractedAt": "2025-12-08T08:24:31.056525+00:00",
      "extractedBy": "github-pages-crawler"
    },
    {
      "id": "瑞士联邦政府_1_1765182271",
      "title": "News Service BundNews Service BundThe portal of the Swiss government",
      "titleChinese": "News Service BundNews Service BundThe portal of the Swiss government",
      "source": "瑞士联邦政府",
      "url": "https://www.admin.ch/en",
      "publishTime": "2025-12-08T08:24:31.056497+00:00",
      "category": "government",
      "language": "en",
      "extractedAt": "2025-12-08T08:24:31.056499+00:00",
      "extractedBy": "github-pages-crawler"
    },
    {
      "id": "瑞士联邦政府_0_1765182271",
      "title": "Skip to main content",
      "titleChinese": "Skip to main content",
      "source": "瑞士联邦政府",
      "url": "https://www.admin.ch#main-content",
      "publishTime": "2025-12-08T08:24:31.056461+00:00",
      "category": "government",
      "language": "en",
      "extractedAt": "2025-12-08T08:24:31.056480+00:00",
      "extractedBy": "github-pages-crawler"
    }
  ]
}