{
  "lastUpdated": "2025-12-18T04:29:55.045771+00:00",
  "totalCount": 10,
  "version": "1.0.0",
  "source": "GitHub Pages Crawler",
  "news": [
    {
      "id": "瑞士联邦政府_13_1766032192",
      "title": "More about «Solid-state cooling takes off: Ionic Wind secures US $2.1M to industrialize technology»",
      "titleChinese": "More about «Solid-state cooling takes off: Ionic Wind secures US $2.1M to industrialize technology»",
      "source": "瑞士联邦政府",
      "url": "https://www.admin.ch/en/newnsb/GlYavDa_w4aQmpsOO565s",
      "publishTime": "2025-12-18T04:29:52.785003+00:00",
      "category": "government",
      "language": "en",
      "extractedAt": "2025-12-18T04:29:52.785004+00:00",
      "extractedBy": "github-pages-crawler"
    },
    {
      "id": "瑞士联邦政府_12_1766032192",
      "title": "More about «Economic forecast: outlook improves slightly»",
      "titleChinese": "More about «Economic forecast: outlook improves slightly»",
      "source": "瑞士联邦政府",
      "url": "https://www.admin.ch/en/newnsb/3RZMH1S0Mlt2iFkVsu9-Y",
      "publishTime": "2025-12-18T04:29:52.784993+00:00",
      "category": "government",
      "language": "en",
      "extractedAt": "2025-12-18T04:29:52.784995+00:00",
      "extractedBy": "github-pages-crawler"
    },
    {
      "id": "瑞士联邦政府_11_1766032192",
      "title": "More about «UNHCR: Global Refugee Forum Progress Review (fr)»",
      "titleChinese": "More about «UNHCR: Global Refugee Forum Progress Review (fr)»",
      "source": "瑞士联邦政府",
      "url": "https://www.admin.ch/en/newnsb/WcKzfhPF7NHQ_1yV0DnIL",
      "publishTime": "2025-12-18T04:29:52.784983+00:00",
      "category": "government",
      "language": "en",
      "extractedAt": "2025-12-18T04:29:52.784985+00:00",
      "extractedBy": "github-pages-crawler"
    },
    {
      "id": "瑞士联邦政府_10_1766032192",
      "title": "More about «Newsletter 482 (15.12.2025)»",
      "titleChinese": "More about «Newsletter 482 (15.12.2025)»",
      "source": "瑞士联邦政府",
      "url": "https://www.admin.ch/en/newnsb/Hg0M-UjGRn9v",
      "publishTime": "2025-12-18T04:29:52.784969+00:00",
      "category": "government",
      "language": "en",
      "extractedAt": "2025-12-18T04:29:52.784976+00:00",
      "extractedBy": "github-pages-crawler"
    },
    {
      "id": "瑞士联邦政府_9_1766032192",
      "title": "More about «Thin interlayers strengthen flexible composite materials: Cool satellites and flexible electronics»",
      "titleChinese": "More about «Thin interlayers strengthen flexible composite materials: Cool satellites and flexible electronics»",
      "source": "瑞士联邦政府",
      "url": "https://www.admin.ch/en/newnsb/T7199A8y4n4ceESgUYJ_q",
      "publishTime": "2025-12-18T04:29:52.784961+00:00",
      "category": "government",
      "language": "en",
      "extractedAt": "2025-12-18T04:29:52.784962+00:00",
      "extractedBy": "github-pages-crawler"
    },
    {
      "id": "瑞士联邦政府_8_1766032192",
      "title": "More about «Switzerland signs Convention establishing International Claims Commission for Ukraine»",
      "titleChinese": "More about «Switzerland signs Convention establishing International Claims Commission for Ukraine»",
      "source": "瑞士联邦政府",
      "url": "https://www.admin.ch/en/newnsb/KL-GQII6C6BDh2ENuTGGw",
      "publishTime": "2025-12-18T04:29:52.784952+00:00",
      "category": "government",
      "language": "en",
      "extractedAt": "2025-12-18T04:29:52.784953+00:00",
      "extractedBy": "github-pages-crawler"
    },
    {
      "id": "瑞士联邦政府_7_1766032192",
      "title": "More about «New STSB final report (cable car) available»",
      "titleChinese": "More about «New STSB final report (cable car) available»",
      "source": "瑞士联邦政府",
      "url": "https://www.admin.ch/en/newnsb/Wu76urz4ogxdpMml7fIEF",
      "publishTime": "2025-12-18T04:29:52.784941+00:00",
      "category": "government",
      "language": "en",
      "extractedAt": "2025-12-18T04:29:52.784943+00:00",
      "extractedBy": "github-pages-crawler"
    },
    {
      "id": "瑞士联邦政府_6_1766032192",
      "title": "More about «Taskforce Drones tests the technological maturity of attack and defence drones»",
      "titleChinese": "More about «Taskforce Drones tests the technological maturity of attack and defence drones»",
      "source": "瑞士联邦政府",
      "url": "https://www.admin.ch/en/newnsb/yxSch-tc_pUdgaHa_UL07",
      "publishTime": "2025-12-18T04:29:52.784928+00:00",
      "category": "government",
      "language": "en",
      "extractedAt": "2025-12-18T04:29:52.784929+00:00",
      "extractedBy": "github-pages-crawler"
    },
    {
      "id": "瑞士联邦政府_1_1766032192",
      "title": "News Service BundNews Service BundThe portal of the Swiss government",
      "titleChinese": "News Service BundNews Service BundThe portal of the Swiss government",
      "source": "瑞士联邦政府",
      "url": "https://www.admin.ch/en",
      "publishTime": "2025-12-18T04:29:52.784900+00:00",
      "category": "government",
      "language": "en",
      "extractedAt": "2025-12-18T04:29:52.784903+00:00",
      "extractedBy": "github-pages-crawler"
    },
    {
      "id": "瑞士联邦政府_0_1766032192",
      "title": "Skip to main content",
      "titleChinese": "Skip to main content",
      "source": "瑞士联邦政府",
      "url": "https://www.admin.ch#main-content",
      "publishTime": "2025-12-18T04:29:52.784858+00:00",
      "category": "government",
      "language": "en",
      "extractedAt": "2025-12-18T04:29:52.784882+00:00",
      "extractedBy": "github-pages-crawler"
    }
  ]
}