{
  "lastUpdated": "2026-02-22T10:19:38.573241+00:00",
  "totalCount": 10,
  "version": "1.0.0",
  "source": "GitHub Pages Crawler",
  "news": [
    {
      "id": "瑞士联邦政府_14_1771755576",
      "title": "More about «Ordinance on measures against individuals and entities who support Hamas or the Palestinian Islamic Jihad»",
      "titleChinese": "More about «Ordinance on measures against individuals and entities who support Hamas or the Palestinian Islamic Jihad»",
      "source": "瑞士联邦政府",
      "url": "https://www.admin.ch/en/newnsb/M5De-GA4uzKeqZBXgJnYS",
      "publishTime": "2026-02-22T10:19:36.254407+00:00",
      "category": "government",
      "language": "en",
      "extractedAt": "2026-02-22T10:19:36.254409+00:00",
      "extractedBy": "github-pages-crawler"
    },
    {
      "id": "瑞士联邦政府_13_1771755576",
      "title": "More about «Sanctions: Ordinance on measures against Sudan»",
      "titleChinese": "More about «Sanctions: Ordinance on measures against Sudan»",
      "source": "瑞士联邦政府",
      "url": "https://www.admin.ch/en/newnsb/0QojJq3LcBkOUl6-tlsAU",
      "publishTime": "2026-02-22T10:19:36.254398+00:00",
      "category": "government",
      "language": "en",
      "extractedAt": "2026-02-22T10:19:36.254400+00:00",
      "extractedBy": "github-pages-crawler"
    },
    {
      "id": "瑞士联邦政府_12_1771755576",
      "title": "More about «Continuation of wastewater monitoring secured»",
      "titleChinese": "More about «Continuation of wastewater monitoring secured»",
      "source": "瑞士联邦政府",
      "url": "https://www.admin.ch/en/newnsb/R2tqovVEDanDLYutVVHaX",
      "publishTime": "2026-02-22T10:19:36.254390+00:00",
      "category": "government",
      "language": "en",
      "extractedAt": "2026-02-22T10:19:36.254392+00:00",
      "extractedBy": "github-pages-crawler"
    },
    {
      "id": "瑞士联邦政府_11_1771755576",
      "title": "More about «Novel strengthening system for reinforced concrete bridges: Retrofitting bridges with “smart” steel»",
      "titleChinese": "More about «Novel strengthening system for reinforced concrete bridges: Retrofitting bridges with “smart” steel»",
      "source": "瑞士联邦政府",
      "url": "https://www.admin.ch/en/newnsb/U8fZ2A9BGpEFd1twDbnkD",
      "publishTime": "2026-02-22T10:19:36.254381+00:00",
      "category": "government",
      "language": "en",
      "extractedAt": "2026-02-22T10:19:36.254383+00:00",
      "extractedBy": "github-pages-crawler"
    },
    {
      "id": "瑞士联邦政府_10_1771755576",
      "title": "More about «IC Forum 2026 in Geneva – challenges and the future of humanitarian aid»",
      "titleChinese": "More about «IC Forum 2026 in Geneva – challenges and the future of humanitarian aid»",
      "source": "瑞士联邦政府",
      "url": "https://www.admin.ch/en/newnsb/9-G1dUkclr3qlPcIUUWdi",
      "publishTime": "2026-02-22T10:19:36.254373+00:00",
      "category": "government",
      "language": "en",
      "extractedAt": "2026-02-22T10:19:36.254375+00:00",
      "extractedBy": "github-pages-crawler"
    },
    {
      "id": "瑞士联邦政府_9_1771755576",
      "title": "More about «President Parmelin meets Indian Prime Minister Modi in New Delhi, announces 2027 AI summit for Geneva»",
      "titleChinese": "More about «President Parmelin meets Indian Prime Minister Modi in New Delhi, announces 2027 AI summit for Geneva»",
      "source": "瑞士联邦政府",
      "url": "https://www.admin.ch/en/newnsb/YZYU1gmqW9vcPFMl2VroY",
      "publishTime": "2026-02-22T10:19:36.254363+00:00",
      "category": "government",
      "language": "en",
      "extractedAt": "2026-02-22T10:19:36.254365+00:00",
      "extractedBy": "github-pages-crawler"
    },
    {
      "id": "瑞士联邦政府_8_1771755576",
      "title": "More about «Emna da la lingua rumantscha (IT)»",
      "titleChinese": "More about «Emna da la lingua rumantscha (IT)»",
      "source": "瑞士联邦政府",
      "url": "https://www.admin.ch/en/newnsb/5vc1tytz_O2nXdwVfEKOg",
      "publishTime": "2026-02-22T10:19:36.254354+00:00",
      "category": "government",
      "language": "en",
      "extractedAt": "2026-02-22T10:19:36.254356+00:00",
      "extractedBy": "github-pages-crawler"
    },
    {
      "id": "瑞士联邦政府_7_1771755576",
      "title": "More about «OSCE press release: OSCE Chairman-in-Office Ignazio Cassis in Bosnia and Herzegovina»",
      "titleChinese": "More about «OSCE press release: OSCE Chairman-in-Office Ignazio Cassis in Bosnia and Herzegovina»",
      "source": "瑞士联邦政府",
      "url": "https://www.admin.ch/en/newnsb/HzFRLaq_HjMWBWQ3B8I2S",
      "publishTime": "2026-02-22T10:19:36.254341+00:00",
      "category": "government",
      "language": "en",
      "extractedAt": "2026-02-22T10:19:36.254343+00:00",
      "extractedBy": "github-pages-crawler"
    },
    {
      "id": "瑞士联邦政府_1_1771755576",
      "title": "News Service BundNews Service BundThe portal of the Swiss government",
      "titleChinese": "News Service BundNews Service BundThe portal of the Swiss government",
      "source": "瑞士联邦政府",
      "url": "https://www.admin.ch/en",
      "publishTime": "2026-02-22T10:19:36.254309+00:00",
      "category": "government",
      "language": "en",
      "extractedAt": "2026-02-22T10:19:36.254311+00:00",
      "extractedBy": "github-pages-crawler"
    },
    {
      "id": "瑞士联邦政府_0_1771755576",
      "title": "Skip to main content",
      "titleChinese": "Skip to main content",
      "source": "瑞士联邦政府",
      "url": "https://www.admin.ch#main-content",
      "publishTime": "2026-02-22T10:19:36.254272+00:00",
      "category": "government",
      "language": "en",
      "extractedAt": "2026-02-22T10:19:36.254291+00:00",
      "extractedBy": "github-pages-crawler"
    }
  ]
}