{
  "lastUpdated": "2026-03-16T07:09:21.010569+00:00",
  "totalCount": 10,
  "version": "1.0.0",
  "source": "GitHub Pages Crawler",
  "news": [
    {
      "id": "瑞士联邦政府_14_1773644958",
      "title": "More about «The FDFA temporarily closes its embassy in Iran»",
      "titleChinese": "More about «The FDFA temporarily closes its embassy in Iran»",
      "source": "瑞士联邦政府",
      "url": "https://www.admin.ch/en/newnsb/UQv9oqfH6pHXEQ9f77ziE",
      "publishTime": "2026-03-16T07:09:18.773980+00:00",
      "category": "government",
      "language": "en",
      "extractedAt": "2026-03-16T07:09:18.773981+00:00",
      "extractedBy": "github-pages-crawler"
    },
    {
      "id": "瑞士联邦政府_13_1773644958",
      "title": "More about «Sanctions: Ordinance on measures against individuals and groups associated with the Taliban»",
      "titleChinese": "More about «Sanctions: Ordinance on measures against individuals and groups associated with the Taliban»",
      "source": "瑞士联邦政府",
      "url": "https://www.admin.ch/en/newnsb/lI4ZDItwt9LH0CttjSfDQ",
      "publishTime": "2026-03-16T07:09:18.773973+00:00",
      "category": "government",
      "language": "en",
      "extractedAt": "2026-03-16T07:09:18.773974+00:00",
      "extractedBy": "github-pages-crawler"
    },
    {
      "id": "瑞士联邦政府_12_1773644958",
      "title": "More about «The nano-lasagna: Novel 2D materials gain momentum»",
      "titleChinese": "More about «The nano-lasagna: Novel 2D materials gain momentum»",
      "source": "瑞士联邦政府",
      "url": "https://www.admin.ch/en/newnsb/AmJBSna1ZjpEiwKyAQzsd",
      "publishTime": "2026-03-16T07:09:18.773966+00:00",
      "category": "government",
      "language": "en",
      "extractedAt": "2026-03-16T07:09:18.773967+00:00",
      "extractedBy": "github-pages-crawler"
    },
    {
      "id": "瑞士联邦政府_11_1773644958",
      "title": "More about «The Swiss Science Council submits statement on planned abolition – Independent advice must not be weakened»",
      "titleChinese": "More about «The Swiss Science Council submits statement on planned abolition – Independent advice must not be weakened»",
      "source": "瑞士联邦政府",
      "url": "https://www.admin.ch/en/newnsb/EYhgan5v3nuSnlnQe3T1u",
      "publishTime": "2026-03-16T07:09:18.773959+00:00",
      "category": "government",
      "language": "en",
      "extractedAt": "2026-03-16T07:09:18.773960+00:00",
      "extractedBy": "github-pages-crawler"
    },
    {
      "id": "瑞士联邦政府_10_1773644958",
      "title": "More about «Federal Council adopts report on foreign policy implications of growing antisemitism in Switzerland»",
      "titleChinese": "More about «Federal Council adopts report on foreign policy implications of growing antisemitism in Switzerland»",
      "source": "瑞士联邦政府",
      "url": "https://www.admin.ch/en/newnsb/day8axBsjFcjNfMXUuC_O",
      "publishTime": "2026-03-16T07:09:18.773951+00:00",
      "category": "government",
      "language": "en",
      "extractedAt": "2026-03-16T07:09:18.773952+00:00",
      "extractedBy": "github-pages-crawler"
    },
    {
      "id": "瑞士联邦政府_9_1773644958",
      "title": "More about «Protection against designer drugs: Further psychoactive substances prohibited»",
      "titleChinese": "More about «Protection against designer drugs: Further psychoactive substances prohibited»",
      "source": "瑞士联邦政府",
      "url": "https://www.admin.ch/en/newnsb/hXmiCIcEHgjJ4_gD3IllM",
      "publishTime": "2026-03-16T07:09:18.773943+00:00",
      "category": "government",
      "language": "en",
      "extractedAt": "2026-03-16T07:09:18.773944+00:00",
      "extractedBy": "github-pages-crawler"
    },
    {
      "id": "瑞士联邦政府_8_1773644958",
      "title": "More about «Federal Council approves addendum I to 2026 budget»",
      "titleChinese": "More about «Federal Council approves addendum I to 2026 budget»",
      "source": "瑞士联邦政府",
      "url": "https://www.admin.ch/en/newnsb/bTh9flGLT1oftF0Z7LxhQ",
      "publishTime": "2026-03-16T07:09:18.773934+00:00",
      "category": "government",
      "language": "en",
      "extractedAt": "2026-03-16T07:09:18.773936+00:00",
      "extractedBy": "github-pages-crawler"
    },
    {
      "id": "瑞士联邦政府_7_1773644958",
      "title": "More about «Federal Council adopts the ‘Stabilisation and further development of Swiss–EU relations’ package»",
      "titleChinese": "More about «Federal Council adopts the ‘Stabilisation and further development of Swiss–EU relations’ package»",
      "source": "瑞士联邦政府",
      "url": "https://www.admin.ch/en/newnsb/HWvQ3sxWQ8hU-xZ4yDnSf",
      "publishTime": "2026-03-16T07:09:18.773923+00:00",
      "category": "government",
      "language": "en",
      "extractedAt": "2026-03-16T07:09:18.773926+00:00",
      "extractedBy": "github-pages-crawler"
    },
    {
      "id": "瑞士联邦政府_1_1773644958",
      "title": "News Service BundNews Service BundThe portal of the Swiss government",
      "titleChinese": "News Service BundNews Service BundThe portal of the Swiss government",
      "source": "瑞士联邦政府",
      "url": "https://www.admin.ch/en",
      "publishTime": "2026-03-16T07:09:18.773893+00:00",
      "category": "government",
      "language": "en",
      "extractedAt": "2026-03-16T07:09:18.773895+00:00",
      "extractedBy": "github-pages-crawler"
    },
    {
      "id": "瑞士联邦政府_0_1773644958",
      "title": "Skip to main content",
      "titleChinese": "Skip to main content",
      "source": "瑞士联邦政府",
      "url": "https://www.admin.ch#main-content",
      "publishTime": "2026-03-16T07:09:18.773858+00:00",
      "category": "government",
      "language": "en",
      "extractedAt": "2026-03-16T07:09:18.773877+00:00",
      "extractedBy": "github-pages-crawler"
    }
  ]
}