{
  "lastUpdated": "2026-03-21T22:18:29.219492+00:00",
  "totalCount": 10,
  "version": "1.0.0",
  "source": "GitHub Pages Crawler",
  "news": [
    {
      "id": "瑞士联邦政府_14_1774131506",
      "title": "More about «OSCE press release: OSCE participating States adopt 2026 Budget»",
      "titleChinese": "More about «OSCE press release: OSCE participating States adopt 2026 Budget»",
      "source": "瑞士联邦政府",
      "url": "https://www.admin.ch/en/newnsb/iX7OJHahBCsC3FRvLUG0x",
      "publishTime": "2026-03-21T22:18:26.941690+00:00",
      "category": "government",
      "language": "en",
      "extractedAt": "2026-03-21T22:18:26.941691+00:00",
      "extractedBy": "github-pages-crawler"
    },
    {
      "id": "瑞士联邦政府_13_1774131506",
      "title": "More about «ESA Council meeting at delegate level takes place in Switzerland»",
      "titleChinese": "More about «ESA Council meeting at delegate level takes place in Switzerland»",
      "source": "瑞士联邦政府",
      "url": "https://www.admin.ch/en/newnsb/sAUFbCDYdpPtgenlSlaCK",
      "publishTime": "2026-03-21T22:18:26.941678+00:00",
      "category": "government",
      "language": "en",
      "extractedAt": "2026-03-21T22:18:26.941680+00:00",
      "extractedBy": "github-pages-crawler"
    },
    {
      "id": "瑞士联邦政府_12_1774131506",
      "title": "More about «GloBE Information Return (GIR)»",
      "titleChinese": "More about «GloBE Information Return (GIR)»",
      "source": "瑞士联邦政府",
      "url": "https://www.admin.ch/en/newnsb/WKgMTX3-ZzY3RJz-IiSiH",
      "publishTime": "2026-03-21T22:18:26.941671+00:00",
      "category": "government",
      "language": "en",
      "extractedAt": "2026-03-21T22:18:26.941672+00:00",
      "extractedBy": "github-pages-crawler"
    },
    {
      "id": "瑞士联邦政府_11_1774131506",
      "title": "More about «Federal Council reaffirms partnership with four UN organisations»",
      "titleChinese": "More about «Federal Council reaffirms partnership with four UN organisations»",
      "source": "瑞士联邦政府",
      "url": "https://www.admin.ch/en/newnsb/CtxdLz30Lz4rwCaplotFJ",
      "publishTime": "2026-03-21T22:18:26.941663+00:00",
      "category": "government",
      "language": "en",
      "extractedAt": "2026-03-21T22:18:26.941665+00:00",
      "extractedBy": "github-pages-crawler"
    },
    {
      "id": "瑞士联邦政府_10_1774131506",
      "title": "More about «Federal Council lowers interest rates for COVID-19 credits»",
      "titleChinese": "More about «Federal Council lowers interest rates for COVID-19 credits»",
      "source": "瑞士联邦政府",
      "url": "https://www.admin.ch/en/newnsb/lyJwymEktZRvatyu4lH9U",
      "publishTime": "2026-03-21T22:18:26.941655+00:00",
      "category": "government",
      "language": "en",
      "extractedAt": "2026-03-21T22:18:26.941656+00:00",
      "extractedBy": "github-pages-crawler"
    },
    {
      "id": "瑞士联邦政府_9_1774131506",
      "title": "More about «Federal Council approves strategy on combating money laundering and terrorist financing»",
      "titleChinese": "More about «Federal Council approves strategy on combating money laundering and terrorist financing»",
      "source": "瑞士联邦政府",
      "url": "https://www.admin.ch/en/newnsb/mBcrOr2fxTs3RYp-6vLip",
      "publishTime": "2026-03-21T22:18:26.941646+00:00",
      "category": "government",
      "language": "en",
      "extractedAt": "2026-03-21T22:18:26.941648+00:00",
      "extractedBy": "github-pages-crawler"
    },
    {
      "id": "瑞士联邦政府_8_1774131506",
      "title": "More about «Iran conflict: impact on war-relevant exports»",
      "titleChinese": "More about «Iran conflict: impact on war-relevant exports»",
      "source": "瑞士联邦政府",
      "url": "https://www.admin.ch/en/newnsb/eLmLXeiHSswJO0UIAyqb8",
      "publishTime": "2026-03-21T22:18:26.941638+00:00",
      "category": "government",
      "language": "en",
      "extractedAt": "2026-03-21T22:18:26.941639+00:00",
      "extractedBy": "github-pages-crawler"
    },
    {
      "id": "瑞士联邦政府_7_1774131506",
      "title": "More about «SECO: Ordinance on Measures Relating to the Situation in Ukraine»",
      "titleChinese": "More about «SECO: Ordinance on Measures Relating to the Situation in Ukraine»",
      "source": "瑞士联邦政府",
      "url": "https://www.admin.ch/en/newnsb/Pq6pTaZeARsT0NRebyeyh",
      "publishTime": "2026-03-21T22:18:26.941627+00:00",
      "category": "government",
      "language": "en",
      "extractedAt": "2026-03-21T22:18:26.941629+00:00",
      "extractedBy": "github-pages-crawler"
    },
    {
      "id": "瑞士联邦政府_1_1774131506",
      "title": "News Service BundNews Service BundThe portal of the Swiss government",
      "titleChinese": "News Service BundNews Service BundThe portal of the Swiss government",
      "source": "瑞士联邦政府",
      "url": "https://www.admin.ch/en",
      "publishTime": "2026-03-21T22:18:26.941595+00:00",
      "category": "government",
      "language": "en",
      "extractedAt": "2026-03-21T22:18:26.941597+00:00",
      "extractedBy": "github-pages-crawler"
    },
    {
      "id": "瑞士联邦政府_0_1774131506",
      "title": "Skip to main content",
      "titleChinese": "Skip to main content",
      "source": "瑞士联邦政府",
      "url": "https://www.admin.ch#main-content",
      "publishTime": "2026-03-21T22:18:26.941558+00:00",
      "category": "government",
      "language": "en",
      "extractedAt": "2026-03-21T22:18:26.941578+00:00",
      "extractedBy": "github-pages-crawler"
    }
  ]
}